litesplat/core/__init__.py
litesplat/core/camera_model.py
litesplat/core/gaussian_model.py
litesplat/io/COLMAP.py
litesplat/io/__init__.py
litesplat/io/import_gaussians.py
litesplat/utils/__init__.py
litesplat/utils/renderer.py
litesplat-0.1.1.dist-info/licenses/LICENSE
litesplat-0.1.1.dist-info/METADATA
litesplat-0.1.1.dist-info/WHEEL
litesplat-0.1.1.dist-info/top_level.txt
litesplat-0.1.1.dist-info/RECORD
