Metadata-Version: 2.4
Name: litesplat
Version: 0.1.1
Summary: LiteSplat — A minimal, portable Gaussian Splatting sandbox for rapid small-scale experimentation and performance insights in pure Python and Keras.
Author-email: Abhas Kumar Sinha <abhaskumarsinha@gmail.com>
Maintainer-email: Abhas Kumar Sinha <abhaskumarsinha@gmail.com>
License: Apache-2.0
Project-URL: Homepage, https://abhaskumarsinha.github.io
Project-URL: Repository, https://github.com/abhaskumarsinha/litesplat
Project-URL: Issues, https://github.com/abhaskumarsinha/litesplat/issues
Keywords: gaussian-splatting,keras,3d-rendering,neural-rendering,research,python
Classifier: Development Status :: 3 - Alpha
Classifier: Intended Audience :: Science/Research
Classifier: License :: OSI Approved :: Apache Software License
Classifier: Programming Language :: Python :: 3
Classifier: Topic :: Scientific/Engineering :: Artificial Intelligence
Classifier: Topic :: Multimedia :: Graphics :: 3D Modeling
Requires-Python: >=3.9
License-File: LICENSE
Requires-Dist: keras>=3.10
Requires-Dist: numpy>=1.24
Requires-Dist: matplotlib>=3.7
Requires-Dist: tqdm>=4.66
Requires-Dist: Pillow>=10.0
Provides-Extra: dev
Requires-Dist: pytest>=8.0; extra == "dev"
Requires-Dist: jupyter>=1.0; extra == "dev"
Requires-Dist: black>=24.0; extra == "dev"
Requires-Dist: flake8>=7.0; extra == "dev"
Dynamic: license-file
